cli.py
config.py
util.py
bot/__init__.py
bot/models.py
bot/repository.py
bot/service.py
chat/__init__.py
chat/app.py
chat/chat_manager.py
chat/models.py
chat/service.py
chat/importer/openrouter_chat_importer.py
chat/provider/base_provider.py
chat/provider/dify_provider.py
chat/provider/display_manager_mixin.py
chat/provider/openai_format_provider.py
chat/provider/topia_orch_provider.py
chat/repository/__init__.py
chat/repository/cloudflare_d1.py
chat/repository/cloudflare_d1_util.py
chat/repository/factory.py
chat/repository/file.py
chat/utils/message_utils.py
chat/utils/tool_utils.py
cli/__init__.py
cli/__main__.py
cli/display_manager.py
cli/input_manager.py
cli/commands/init.py
cli/commands/bot/__init__.py
cli/commands/bot/add.py
cli/commands/bot/delete.py
cli/commands/bot/list.py
cli/commands/chat/chat.py
cli/commands/chat/import_chat.py
cli/commands/chat/list.py
cli/commands/chat/share.py
cli/commands/daemon/__init__.py
cli/commands/daemon/log.py
cli/commands/daemon/restart.py
cli/commands/daemon/start.py
cli/commands/daemon/status.py
cli/commands/daemon/stop.py
cli/commands/daemon/utils.py
cli/commands/mcp/__init__.py
cli/commands/mcp/add.py
cli/commands/mcp/delete.py
cli/commands/mcp/list.py
cli/commands/prompt/__init__.py
cli/commands/prompt/add.py
cli/commands/prompt/delete.py
cli/commands/prompt/list.py
daemon_client/__init__.py
daemon_client/connection_pool.py
daemon_client/main.py
daemon_client/models.py
mcp_daemon/__init__.py
mcp_daemon/handlers.py
mcp_daemon/main.py
mcp_daemon/models.py
mcp_daemon/server.py
mcp_daemon/sse.py
mcp_daemon/stdio.py
mcp_server/__init__.py
mcp_server/mcp_manager.py
mcp_server/models.py
mcp_server/repository.py
mcp_server/service.py
prompt/__init__.py
prompt/mcp.py
prompt/models.py
prompt/preset.py
prompt/repository.py
prompt/service.py
y_cli-0.4.0.dist-info/licenses/LICENSE
y_cli-0.4.0.dist-info/METADATA
y_cli-0.4.0.dist-info/WHEEL
y_cli-0.4.0.dist-info/entry_points.txt
y_cli-0.4.0.dist-info/top_level.txt
y_cli-0.4.0.dist-info/RECORD
