Metadata-Version: 2.4
Name: y-cli
Version: 0.4.0
Summary: Command-line real-time conversation app
Requires-Python: >=3.10
License-File: LICENSE
Requires-Dist: httpx>=0.26.0
Requires-Dist: prompt-toolkit>=3.0.0
Requires-Dist: click>=8.1.0
Requires-Dist: toml>=0.10.2
Requires-Dist: tabulate>=0.9.0
Requires-Dist: wcwidth>=0.2.13
Requires-Dist: rich>=13.9.4
Requires-Dist: pyperclip>=1.9.0
Requires-Dist: mcp>=1.2.1
Requires-Dist: aiofiles>=24.1.0
Requires-Dist: loguru>=0.7.3
Dynamic: license-file
